build.cp35-win32.pyd
geatpy/Algorithm.py
geatpy/Population.py
geatpy/Problem.py
geatpy/PsyPopulation.py
geatpy/__init__.py
geatpy/optimize.py
geatpy/algorithms/moeas/awGA/moea_awGA_templet.py
geatpy/algorithms/moeas/awGA/moea_psy_awGA_templet.py
geatpy/algorithms/moeas/awGA/updateNDSet.py
geatpy/algorithms/moeas/moead/moea_MOEAD_DE_templet.py
geatpy/algorithms/moeas/moead/moea_MOEAD_archive_templet.py
geatpy/algorithms/moeas/moead/moea_MOEAD_templet.py
geatpy/algorithms/moeas/nsga2/moea_NSGA2_DE_templet.py
geatpy/algorithms/moeas/nsga2/moea_NSGA2_archive_templet.py
geatpy/algorithms/moeas/nsga2/moea_NSGA2_templet.py
geatpy/algorithms/moeas/nsga2/moea_psy_NSGA2_archive_templet.py
geatpy/algorithms/moeas/nsga2/moea_psy_NSGA2_templet.py
geatpy/algorithms/moeas/nsga3/moea_NSGA3_DE_templet.py
geatpy/algorithms/moeas/nsga3/moea_NSGA3_templet.py
geatpy/algorithms/moeas/nsga3/moea_psy_NSGA3_templet.py
geatpy/algorithms/moeas/pps/moea_PPS_MOEAD_DE_archive_templet.py
geatpy/algorithms/moeas/rvea/moea_RVEA_RES_templet.py
geatpy/algorithms/moeas/rvea/moea_RVEA_templet.py
geatpy/algorithms/moeas/rvea/moea_psy_RVEA_RES_templet.py
geatpy/algorithms/moeas/rvea/moea_psy_RVEA_templet.py
geatpy/algorithms/soeas/DE/DE_best_1_L/soea_DE_best_1_L_templet.py
geatpy/algorithms/soeas/DE/DE_best_1_bin/soea_DE_best_1_bin_templet.py
geatpy/algorithms/soeas/DE/DE_currentToBest_1_L/soea_DE_currentToBest_1_L_templet.py
geatpy/algorithms/soeas/DE/DE_currentToBest_1_bin/soea_DE_currentToBest_1_bin_templet.py
geatpy/algorithms/soeas/DE/DE_currentToRand_1/soea_DE_currentToRand_1_templet.py
geatpy/algorithms/soeas/DE/DE_rand_1_L/soea_DE_rand_1_L_templet.py
geatpy/algorithms/soeas/DE/DE_rand_1_bin/soea_DE_rand_1_bin_templet.py
geatpy/algorithms/soeas/DE/DE_targetToBest_1_L/soea_DE_targetToBest_1_L_templet.py
geatpy/algorithms/soeas/DE/DE_targetToBest_1_bin/soea_DE_targetToBest_1_bin_templet.py
geatpy/algorithms/soeas/ES/ES_1_plus_1/soea_ES_1_plus_1_templet.py
geatpy-2.7.0.dist-info/METADATA
geatpy-2.7.0.dist-info/WHEEL
geatpy-2.7.0.dist-info/top_level.txt
geatpy-2.7.0.dist-info/RECORD
